strabs/doit/__init__.py
strabs/doit/py.typed
strabs_doit-0.1.3.dist-info/METADATA
strabs_doit-0.1.3.dist-info/WHEEL
strabs_doit-0.1.3.dist-info/RECORD
