Metadata-Version: 2.4
Name: strabs-doit
Version: 0.1.3
Summary: For when you just want to get stuff done. Task runner with parallel execution.
Requires-Python: >=3.10
Requires-Dist: rich>=14.0
Provides-Extra: dev
Requires-Dist: mypy>=1.19; extra == 'dev'
Requires-Dist: pytest>=9.0; extra == 'dev'
Requires-Dist: ruff>=0.14; extra == 'dev'
